[
    {
        "domain": ".bing.com",
        "expirationDate": 1725085118.019903,
        "hostOnly": false,
        "httpOnly": false,
        "name": "SnrOvr",
        "path": "/",
        "sameSite": "no_restriction",
        "secure": true,
        "session": false,
        "storeId": null,
        "value": "X=rebateson"
    },
    {
        "domain": ".bing.com",
        "expirationDate": 1728022717.250803,
        "hostOnly": false,
        "httpOnly": false,
        "name": "SRCHUSR",
        "path": "/",
        "sameSite": "no_restriction",
        "secure": true,
        "session": false,
        "storeId": null,
        "value": "DOB=20230808&T=1693462713000"
    },
    {
        "domain": ".bing.com",
        "hostOnly": false,
        "httpOnly": true,
        "name": "_Rwho",
        "path": "/",
        "sameSite": "no_restriction",
        "secure": true,
        "session": true,
        "storeId": null,
        "value": "u=d"
    },
    {
        "domain": ".bing.com",
        "expirationDate": 1693464392.432621,
        "hostOnly": false,
        "httpOnly": false,
        "name": "GC",
        "path": "/",
        "sameSite": "no_restriction",
        "secure": true,
        "session": false,
        "storeId": null,
        "value": "DU8XZX7wV1FU1w3be7qZHdM6CZPKA0uQlF67PKQyrLrGIQe8e7PNdkuutf5UmjL2iRfsrs0Si9gnZXY1PanW9Q"
    },
    {
        "domain": ".bing.com",
        "expirationDate": 1693505900.022232,
        "hostOnly": false,
        "httpOnly": true,
        "name": "SUID",
        "path": "/",
        "sameSite": "no_restriction",
        "secure": true,
        "session": false,
        "storeId": null,
        "value": "A"
    },
    {
        "domain": ".bing.com",
        "expirationDate": 1725932117.435391,
        "hostOnly": false,
        "httpOnly": true,
        "name": "_EDGE_CD",
        "path": "/",
        "sameSite": null,
        "secure": false,
        "session": false,
        "storeId": null,
        "value": "u=zh-hans"
    },
    {
        "domain": ".bing.com",
        "expirationDate": 1693464423.221088,
        "hostOnly": false,
        "httpOnly": false,
        "name": "cct",
        "path": "/",
        "sameSite": "no_restriction",
        "secure": true,
        "session": false,
        "storeId": null,
        "value": "DU8XZX7wV1FU1w3be7qZHdM6CZPKA0uQlF67PKQyrLoWjqC7FN_5riwIEwJU_XA3tgEH1poRDgfNTNNP7knmpg"
    },
    {
        "domain": ".bing.com",
        "expirationDate": 1728022774.338873,
        "hostOnly": false,
        "httpOnly": false,
        "name": "SRCHHPGUSR",
        "path": "/",
        "sameSite": "no_restriction",
        "secure": true,
        "session": false,
        "storeId": null,
        "value": "SRCHLANG=zh-Hans&DM=1&THEME=1&HV=1693462774&WTS=63827775392&PV=15.0.0&BZA=0&BRW=N&BRH=S&CW=1232&CH=598&SCW=1232&SCH=796&DPR=1.5&UTC=480&EXLTT=12&PRVCW=1232&PRVCH=598&IG=C9EA041CB77E4EA4A905FB79421F8BD8&cdxwinturn=3&cdxtone=Creative&cdxtoneopts=h3imaginative,clgalileo,gencontentv3,fluxv1plus"
    },
    {
        "domain": ".bing.com",
        "expirationDate": 1728022700.02243,
        "hostOnly": false,
        "httpOnly": false,
        "name": "ANON",
        "path": "/",
        "sameSite": "no_restriction",
        "secure": true,
        "session": false,
        "storeId": null,
        "value": "A=E8E91F07B00230D096ED32F2FFFFFFFF&E=1cb3&W=1"
    },
    {
        "domain": ".bing.com",
        "hostOnly": false,
        "httpOnly": false,
        "name": "_SS",
        "path": "/",
        "sameSite": "no_restriction",
        "secure": true,
        "session": true,
        "storeId": null,
        "value": "SID=0759CAAD5A1E6CF4144AD9D35B906D02&R=15&RB=15&GB=0&RG=0&RP=15"
    },
    {
        "domain": ".bing.com",
        "hostOnly": false,
        "httpOnly": false,
        "name": "ipv6",
        "path": "/",
        "sameSite": "no_restriction",
        "secure": true,
        "session": true,
        "storeId": null,
        "value": "hit=1693466321651&t=4"
    },
    {
        "domain": ".bing.com",
        "expirationDate": 1694672300.0224,
        "hostOnly": false,
        "httpOnly": false,
        "name": "_U",
        "path": "/",
        "sameSite": "no_restriction",
        "secure": true,
        "session": false,
        "storeId": null,
        "value": ""
    },
    {
        "domain": ".bing.com",
        "expirationDate": 1726046714.315055,
        "hostOnly": false,
        "httpOnly": false,
        "name": "SRCHD",
        "path": "/",
        "sameSite": "no_restriction",
        "secure": true,
        "session": false,
        "storeId": null,
        "value": "AF=SHORUN"
    },
    {
        "domain": ".bing.com",
        "expirationDate": 1707731326.178461,
        "hostOnly": false,
        "httpOnly": false,
        "name": "NAP",
        "path": "/",
        "sameSite": "no_restriction",
        "secure": true,
        "session": false,
        "storeId": null,
        "value": "V=1.9&E=1c59&C=mu9vNxqbj2cUDrbroAzgohX8SC17t5nGO9Zfg1BybFHJWXGgPBoFlQ&W=1"
    },
    {
        "domain": ".bing.com",
        "expirationDate": 1725085118.019805,
        "hostOnly": false,
        "httpOnly": false,
        "name": "_RwBf",
        "path": "/",
        "sameSite": "no_restriction",
        "secure": true,
        "session": false,
        "storeId": null,
        "value": "r=1&ilt=2&ihpd=0&ispd=2&rc=15&rb=15&gb=0&rg=0&pc=15&mtu=0&rbb=0.0&g=0&cid=&clo=0&v=1&l=2023-08-30T07:00:00.0000000Z&lft=0001-01-01T00:00:00.0000000&aof=0&o=0&p=BINGCOPILOTWAITLIST&c=MR000T&t=9407&s=2023-08-16T10:04:34.8063452+00:00&ts=2023-08-31T06:18:37.8838828+00:00&rwred=0&wls=2&wlb=0&lka=0&lkt=0&TH=&dci=0&mta=0&e=II8xNCDvZbIjXDMIRYoGGVRSD6OdUy6gbTASuJie25zRi2mGaD9bXiqJhi-rThSu58nPwtlIoJlMAj_rqr74dMdMq9tLMN1MwMWSbodX5bo&A="
    },
    {
        "domain": ".bing.com",
        "expirationDate": 1726814809.424011,
        "hostOnly": false,
        "httpOnly": false,
        "name": "_UR",
        "path": "/",
        "sameSite": "no_restriction",
        "secure": true,
        "session": false,
        "storeId": null,
        "value": "QS=0&TQS=0"
    },
    {
        "domain": ".bing.com",
        "hostOnly": false,
        "httpOnly": true,
        "name": "_EDGE_S",
        "path": "/",
        "sameSite": null,
        "secure": false,
        "session": true,
        "storeId": null,
        "value": "SID=0759CAAD5A1E6CF4144AD9D35B906D02"
    },
    {
        "domain": "www.bing.com",
        "expirationDate": 1727158719.724346,
        "hostOnly": true,
        "httpOnly": true,
        "name": "MUIDB",
        "path": "/",
        "sameSite": null,
        "secure": false,
        "session": false,
        "storeId": null,
        "value": "36A7750FEFC26ED118136650EE816F3B"
    },
    {
        "domain": ".bing.com",
        "expirationDate": 1727937979.800589,
        "hostOnly": false,
        "httpOnly": true,
        "name": "USRLOC",
        "path": "/",
        "sameSite": "no_restriction",
        "secure": true,
        "session": false,
        "storeId": null,
        "value": "HS=1&ELOC=LAT=34.044761657714844|LON=-118.2527084350586|N=%E6%B4%9B%E6%9D%89%E7%9F%B6%EF%BC%8C%E5%8A%A0%E5%88%A9%E7%A6%8F%E5%B0%BC%E4%BA%9A|ELT=1|&CLOC=LAT=31.9887|LON=118.7395|A=1353|TS=230830074137|SRC=I"
    },
    {
        "domain": ".bing.com",
        "expirationDate": 1726814812.075287,
        "hostOnly": false,
        "httpOnly": false,
        "name": "_HPVN",
        "path": "/",
        "sameSite": "no_restriction",
        "secure": true,
        "session": false,
        "storeId": null,
        "value": "CS=eyJQbiI6eyJDbiI6MSwiU3QiOjAsIlFzIjowLCJQcm9kIjoiUCJ9LCJTYyI6eyJDbiI6MSwiU3QiOjAsIlFzIjowLCJQcm9kIjoiSCJ9LCJReiI6eyJDbiI6MSwiU3QiOjAsIlFzIjowLCJQcm9kIjoiVCJ9LCJBcCI6dHJ1ZSwiTXV0ZSI6dHJ1ZSwiTGFkIjoiMjAyMy0wOC0xN1QwMDowMDowMCIsIklvdGQiOjAsIkd3YiI6MCwiRGZ0IjpudWxsLCJNdnMiOjAsIkZsdCI6MCwiSW1wIjozfQ=="
    },
    {
        "domain": ".bing.com",
        "expirationDate": 1726623494.757948,
        "hostOnly": false,
        "httpOnly": false,
        "name": "MUID",
        "path": "/",
        "sameSite": "no_restriction",
        "secure": true,
        "session": false,
        "storeId": null,
        "value": "36A7750FEFC26ED118136650EE816F3B"
    },
    {
        "domain": ".bing.com",
        "expirationDate": 1726046714.315064,
        "hostOnly": false,
        "httpOnly": false,
        "name": "SRCHUID",
        "path": "/",
        "sameSite": "no_restriction",
        "secure": true,
        "session": false,
        "storeId": null,
        "value": "V=2&GUID=F6896BC91B9043A39CE34386CD34CADA&dmnchg=1"
    },
    {
        "domain": ".bing.com",
        "hostOnly": false,
        "httpOnly": false,
        "name": "WLS",
        "path": "/",
        "sameSite": "no_restriction",
        "secure": true,
        "session": true,
        "storeId": null,
        "value": "C=30b40f61eeec541f&N=KK"
    }
]